tests/__init__.py
tests/test.py
typehint/__init__.py
typehint/typehint.py
pymdown_typehint-0.2.0.dist-info/LICENSE
pymdown_typehint-0.2.0.dist-info/METADATA
pymdown_typehint-0.2.0.dist-info/WHEEL
pymdown_typehint-0.2.0.dist-info/entry_points.txt
pymdown_typehint-0.2.0.dist-info/top_level.txt
pymdown_typehint-0.2.0.dist-info/RECORD
