Metadata-Version: 2.1
Name: pymdown-typehint
Version: 0.2.0
Summary: A Python-Markdown extension for styling variable types in-line
Home-page: https://github.com/mghweb/pymdown-typehint
Author: Max Hegler
Author-email: maxghegler@gmail.com
License: MIT License
Platform: UNKNOWN
Classifier: Intended Audience :: Developers
Classifier: Programming Language :: Python :: 3
Classifier: License :: OSI Approved :: MIT License
Classifier: Operating System :: OS Independent
Classifier: Topic :: Software Development :: Libraries :: Python Modules
Classifier: Topic :: Text Processing :: Filters
Classifier: Topic :: Text Processing :: Markup :: HTML
Requires-Python: >3.0
Requires-Dist: Markdown (>=3.2)
